stripper/__init__.py
stripper/text_utils.py
stripper-0.1.5.dist-info/METADATA
stripper-0.1.5.dist-info/WHEEL
stripper-0.1.5.dist-info/top_level.txt
stripper-0.1.5.dist-info/RECORD
