Metadata-Version: 2.1
Name: stripper
Version: 0.1.5
Summary: A simple utility to strip text after a semicolon
Author: Abinesh
Author-email: abineshrseasense@gmail.com
Classifier: Programming Language :: Python :: 3
Classifier: License :: OSI Approved :: MIT License
Classifier: Operating System :: OS Independent
Requires-Python: >=3.6
